{"result":[{"date":"2020-6-4","action":"DS","tot_orders":2,"tot_order_lines":2},{"date":"2020-6-4","action":"SM","tot_orders":1,"tot_order_lines":1},{"date":"2020-6-4","action":"DA","tot_orders":1,"tot_order_lines":1},{"date":"2020-6-5","action":"DA","tot_orders":2,"tot_order_lines":2},{"date":"2020-6-5","action":"SM","tot_orders":14,"tot_order_lines":29},{"date":"2020-6-5","action":"DS","tot_orders":89,"tot_order_lines":148},{"date":"2020-6-5","action":"S","tot_orders":2,"tot_order_lines":4},{"date":"2020-6-6","action":"DS","tot_orders":3,"tot_order_lines":3},{"date":"2020-6-8","action":"S","tot_orders":8,"tot_order_lines":11},{"date":"2020-6-8","action":"DS","tot_orders":164,"tot_order_lines":661},{"date":"2020-6-8","action":"SM","tot_orders":31,"tot_order_lines":207},{"date":"2020-6-8","action":"DA","tot_orders":7,"tot_order_lines":8},{"date":"2020-6-9","action":"S","tot_orders":3,"tot_order_lines":7},{"date":"2020-6-9","action":"DA","tot_orders":7,"tot_order_lines":7},{"date":"2020-6-9","action":"SM","tot_orders":60,"tot_order_lines":299},{"date":"2020-6-9","action":"DS","tot_orders":108,"tot_order_lines":472},{"date":"2020-6-10","action":"SM","tot_orders":48,"tot_order_lines":246},{"date":"2020-6-10","action":"S","tot_orders":3,"tot_order_lines":4},{"date":"2020-6-10","action":"DS","tot_orders":159,"tot_order_lines":455},{"date":"2020-6-10","action":"DA","tot_orders":12,"tot_order_lines":13},{"date":"2020-6-11","action":"SM","tot_orders":36,"tot_order_lines":190},{"date":"2020-6-11","action":"DA","tot_orders":5,"tot_order_lines":5},{"date":"2020-6-11","action":"DS","tot_orders":97,"tot_order_lines":250},{"date":"2020-6-11","action":"S","tot_orders":6,"tot_order_lines":10},{"date":"2020-6-12","action":"S","tot_orders":6,"tot_order_lines":6},{"date":"2020-6-12","action":"DA","tot_orders":4,"tot_order_lines":4},{"date":"2020-6-12","action":"SM","tot_orders":30,"tot_order_lines":40},{"date":"2020-6-12","action":"DS","tot_orders":118,"tot_order_lines":329},{"date":"2020-6-13","action":"DS","tot_orders":1,"tot_order_lines":1},{"date":"2020-6-15","action":"SM","tot_orders":29,"tot_order_lines":105},{"date":"2020-6-15","action":"DS","tot_orders":125,"tot_order_lines":486},{"date":"2020-6-15","action":"S","tot_orders":8,"tot_order_lines":11},{"date":"2020-6-15","action":"DA","tot_orders":4,"tot_order_lines":9},{"date":"2020-6-16","action":"S","tot_orders":10,"tot_order_lines":21},{"date":"2020-6-16","action":"DS","tot_orders":119,"tot_order_lines":267},{"date":"2020-6-16","action":"SM","tot_orders":44,"tot_order_lines":116},{"date":"2020-6-16","action":"DA","tot_orders":1,"tot_order_lines":1},{"date":"2020-6-17","action":"S","tot_orders":8,"tot_order_lines":10},{"date":"2020-6-17","action":"DA","tot_orders":6,"tot_order_lines":6},{"date":"2020-6-17","action":"DS","tot_orders":172,"tot_order_lines":408},{"date":"2020-6-17","action":"SM","tot_orders":40,"tot_order_lines":195},{"date":"2020-6-18","action":"S","tot_orders":1,"tot_order_lines":1},{"date":"2020-6-18","action":"DS","tot_orders":148,"tot_order_lines":276},{"date":"2020-6-18","action":"DA","tot_orders":2,"tot_order_lines":2},{"date":"2020-6-18","action":"SM","tot_orders":41,"tot_order_lines":72},{"date":"2020-6-19","action":"DS","tot_orders":97,"tot_order_lines":218},{"date":"2020-6-19","action":"DA","tot_orders":2,"tot_order_lines":2},{"date":"2020-6-19","action":"S","tot_orders":3,"tot_order_lines":3},{"date":"2020-6-19","action":"SM","tot_orders":30,"tot_order_lines":49},{"date":"2020-6-20","action":"DS","tot_orders":23,"tot_order_lines":24},{"date":"2020-6-22","action":"DA","tot_orders":10,"tot_order_lines":13},{"date":"2020-6-22","action":"SM","tot_orders":57,"tot_order_lines":136},{"date":"2020-6-22","action":"S","tot_orders":6,"tot_order_lines":9},{"date":"2020-6-22","action":"DS","tot_orders":152,"tot_order_lines":427},{"date":"2020-6-23","action":"DA","tot_orders":17,"tot_order_lines":24},{"date":"2020-6-23","action":"DS","tot_orders":176,"tot_order_lines":596},{"date":"2020-6-23","action":"S","tot_orders":3,"tot_order_lines":3},{"date":"2020-6-23","action":"SM","tot_orders":64,"tot_order_lines":260},{"date":"2020-6-24","action":"SM","tot_orders":33,"tot_order_lines":104},{"date":"2020-6-24","action":"S","tot_orders":7,"tot_order_lines":14},{"date":"2020-6-24","action":"DA","tot_orders":6,"tot_order_lines":7},{"date":"2020-6-24","action":"DS","tot_orders":157,"tot_order_lines":400},{"date":"2020-6-25","action":"DA","tot_orders":5,"tot_order_lines":5},{"date":"2020-6-25","action":"DS","tot_orders":116,"tot_order_lines":252},{"date":"2020-6-25","action":"SM","tot_orders":26,"tot_order_lines":83},{"date":"2020-6-25","action":"S","tot_orders":11,"tot_order_lines":18},{"date":"2020-6-26","action":"DS","tot_orders":144,"tot_order_lines":247},{"date":"2020-6-26","action":"SM","tot_orders":47,"tot_order_lines":128},{"date":"2020-6-26","action":"DA","tot_orders":4,"tot_order_lines":4},{"date":"2020-6-26","action":"S","tot_orders":9,"tot_order_lines":10},{"date":"2020-6-27","action":"DS","tot_orders":4,"tot_order_lines":6},{"date":"2020-6-28","action":"SM","tot_orders":1,"tot_order_lines":4},{"date":"2020-6-28","action":"DS","tot_orders":1,"tot_order_lines":1},{"date":"2020-6-29","action":"SM","tot_orders":41,"tot_order_lines":170},{"date":"2020-6-29","action":"DS","tot_orders":190,"tot_order_lines":638},{"date":"2020-6-29","action":"S","tot_orders":8,"tot_order_lines":9},{"date":"2020-6-29","action":"DA","tot_orders":20,"tot_order_lines":22},{"date":"2020-6-30","action":"DA","tot_orders":5,"tot_order_lines":7},{"date":"2020-6-30","action":"SM","tot_orders":45,"tot_order_lines":117},{"date":"2020-6-30","action":"DS","tot_orders":118,"tot_order_lines":361},{"date":"2020-6-30","action":"S","tot_orders":4,"tot_order_lines":6},{"date":"2020-7-1","action":"DA","tot_orders":9,"tot_order_lines":9},{"date":"2020-7-1","action":"DS","tot_orders":235,"tot_order_lines":330},{"date":"2020-7-1","action":"S","tot_orders":14,"tot_order_lines":19},{"date":"2020-7-1","action":"SM","tot_orders":66,"tot_order_lines":284},{"date":"2020-7-2","action":"DA","tot_orders":1,"tot_order_lines":1},{"date":"2020-7-2","action":"S","tot_orders":4,"tot_order_lines":4},{"date":"2020-7-2","action":"DS","tot_orders":120,"tot_order_lines":198},{"date":"2020-7-2","action":"SM","tot_orders":47,"tot_order_lines":147},{"date":"2020-7-3","action":"S","tot_orders":1,"tot_order_lines":1},{"date":"2020-7-3","action":"DS","tot_orders":4,"tot_order_lines":4},{"date":"2020-7-4","action":"DS","tot_orders":1,"tot_order_lines":1},{"date":"2020-7-4","action":"SM","tot_orders":1,"tot_order_lines":1},{"date":"2020-7-6","action":"SM","tot_orders":52,"tot_order_lines":138},{"date":"2020-7-6","action":"S","tot_orders":6,"tot_order_lines":8},{"date":"2020-7-6","action":"DS","tot_orders":199,"tot_order_lines":696},{"date":"2020-7-6","action":"DA","tot_orders":9,"tot_order_lines":9},{"date":"2020-7-7","action":"SM","tot_orders":110,"tot_order_lines":236},{"date":"2020-7-7","action":"DS","tot_orders":135,"tot_order_lines":432},{"date":"2020-7-7","action":"DA","tot_orders":5,"tot_order_lines":6},{"date":"2020-7-7","action":"S","tot_orders":6,"tot_order_lines":6},{"date":"2020-7-8","action":"DA","tot_orders":15,"tot_order_lines":21},{"date":"2020-7-8","action":"SM","tot_orders":50,"tot_order_lines":90},{"date":"2020-7-8","action":"S","tot_orders":5,"tot_order_lines":45},{"date":"2020-7-8","action":"DS","tot_orders":181,"tot_order_lines":376},{"date":"2020-7-9","action":"DS","tot_orders":147,"tot_order_lines":273},{"date":"2020-7-9","action":"S","tot_orders":2,"tot_order_lines":2},{"date":"2020-7-9","action":"SM","tot_orders":114,"tot_order_lines":174},{"date":"2020-7-9","action":"DA","tot_orders":13,"tot_order_lines":17},{"date":"2020-7-10","action":"SM","tot_orders":63,"tot_order_lines":104},{"date":"2020-7-10","action":"S","tot_orders":7,"tot_order_lines":15},{"date":"2020-7-10","action":"DA","tot_orders":9,"tot_order_lines":9},{"date":"2020-7-10","action":"DS","tot_orders":99,"tot_order_lines":201},{"date":"2020-7-11","action":"S","tot_orders":1,"tot_order_lines":5},{"date":"2020-7-11","action":"DS","tot_orders":1,"tot_order_lines":1},{"date":"2020-7-13","action":"DS","tot_orders":189,"tot_order_lines":1273},{"date":"2020-7-13","action":"SM","tot_orders":65,"tot_order_lines":172},{"date":"2020-7-13","action":"DA","tot_orders":20,"tot_order_lines":69},{"date":"2020-7-13","action":"S","tot_orders":11,"tot_order_lines":35},{"date":"2020-7-14","action":"S","tot_orders":5,"tot_order_lines":42},{"date":"2020-7-14","action":"SM","tot_orders":237,"tot_order_lines":421},{"date":"2020-7-14","action":"DS","tot_orders":148,"tot_order_lines":1066},{"date":"2020-7-14","action":"DA","tot_orders":14,"tot_order_lines":14},{"date":"2020-7-15","action":"SM","tot_orders":218,"tot_order_lines":308},{"date":"2020-7-15","action":"S","tot_orders":13,"tot_order_lines":27},{"date":"2020-7-15","action":"DS","tot_orders":155,"tot_order_lines":523},{"date":"2020-7-15","action":"DA","tot_orders":7,"tot_order_lines":15},{"date":"2020-7-16","action":"DA","tot_orders":8,"tot_order_lines":10},{"date":"2020-7-16","action":"SM","tot_orders":128,"tot_order_lines":265},{"date":"2020-7-16","action":"DS","tot_orders":128,"tot_order_lines":303},{"date":"2020-7-16","action":"S","tot_orders":10,"tot_order_lines":15},{"date":"2020-7-17","action":"DS","tot_orders":124,"tot_order_lines":237},{"date":"2020-7-17","action":"S","tot_orders":9,"tot_order_lines":19},{"date":"2020-7-17","action":"DA","tot_orders":9,"tot_order_lines":9},{"date":"2020-7-17","action":"SM","tot_orders":129,"tot_order_lines":218},{"date":"2020-7-18","action":"SM","tot_orders":5,"tot_order_lines":41},{"date":"2020-7-19","action":"SM","tot_orders":1,"tot_order_lines":1},{"date":"2020-7-20","action":"SM","tot_orders":112,"tot_order_lines":296},{"date":"2020-7-20","action":"DA","tot_orders":10,"tot_order_lines":10},{"date":"2020-7-20","action":"DS","tot_orders":230,"tot_order_lines":1143},{"date":"2020-7-20","action":"S","tot_orders":14,"tot_order_lines":15},{"date":"2020-7-21","action":"DA","tot_orders":12,"tot_order_lines":12},{"date":"2020-7-21","action":"S","tot_orders":9,"tot_order_lines":24},{"date":"2020-7-21","action":"DS","tot_orders":206,"tot_order_lines":809},{"date":"2020-7-21","action":"SM","tot_orders":127,"tot_order_lines":251},{"date":"2020-7-22","action":"S","tot_orders":6,"tot_order_lines":35},{"date":"2020-7-22","action":"DA","tot_orders":7,"tot_order_lines":14},{"date":"2020-7-22","action":"DS","tot_orders":174,"tot_order_lines":412},{"date":"2020-7-22","action":"SM","tot_orders":113,"tot_order_lines":286},{"date":"2020-7-23","action":"S","tot_orders":15,"tot_order_lines":19},{"date":"2020-7-23","action":"SM","tot_orders":116,"tot_order_lines":385},{"date":"2020-7-23","action":"DA","tot_orders":6,"tot_order_lines":6},{"date":"2020-7-23","action":"DS","tot_orders":144,"tot_order_lines":662},{"date":"2020-7-24","action":"DA","tot_orders":16,"tot_order_lines":16},{"date":"2020-7-24","action":"SM","tot_orders":124,"tot_order_lines":164},{"date":"2020-7-24","action":"S","tot_orders":9,"tot_order_lines":14},{"date":"2020-7-24","action":"DS","tot_orders":132,"tot_order_lines":242},{"date":"2020-7-25","action":"SM","tot_orders":3,"tot_order_lines":3},{"date":"2020-7-25","action":"DS","tot_orders":2,"tot_order_lines":2},{"date":"2020-7-27","action":"S","tot_orders":58,"tot_order_lines":60},{"date":"2020-7-27","action":"SM","tot_orders":137,"tot_order_lines":397},{"date":"2020-7-27","action":"DS","tot_orders":238,"tot_order_lines":807},{"date":"2020-7-27","action":"DA","tot_orders":6,"tot_order_lines":6},{"date":"2020-7-28","action":"DS","tot_orders":212,"tot_order_lines":942},{"date":"2020-7-28","action":"DA","tot_orders":5,"tot_order_lines":5},{"date":"2020-7-28","action":"SM","tot_orders":128,"tot_order_lines":258},{"date":"2020-7-28","action":"S","tot_orders":9,"tot_order_lines":22},{"date":"2020-7-29","action":"S","tot_orders":19,"tot_order_lines":22},{"date":"2020-7-29","action":"DA","tot_orders":2,"tot_order_lines":2},{"date":"2020-7-29","action":"DS","tot_orders":206,"tot_order_lines":585},{"date":"2020-7-29","action":"SM","tot_orders":134,"tot_order_lines":277},{"date":"2020-7-30","action":"SM","tot_orders":127,"tot_order_lines":260},{"date":"2020-7-30","action":"S","tot_orders":4,"tot_order_lines":6},{"date":"2020-7-30","action":"DS","tot_orders":167,"tot_order_lines":499},{"date":"2020-7-30","action":"DA","tot_orders":3,"tot_order_lines":3},{"date":"2020-7-31","action":"SM","tot_orders":202,"tot_order_lines":404},{"date":"2020-7-31","action":"DS","tot_orders":107,"tot_order_lines":215},{"date":"2020-7-31","action":"DA","tot_orders":3,"tot_order_lines":3},{"date":"2020-8-1","action":"SM","tot_orders":8,"tot_order_lines":32},{"date":"2020-8-2","action":"DS","tot_orders":5,"tot_order_lines":5},{"date":"2020-8-3","action":"SM","tot_orders":137,"tot_order_lines":334},{"date":"2020-8-3","action":"DA","tot_orders":10,"tot_order_lines":16},{"date":"2020-8-3","action":"DS","tot_orders":194,"tot_order_lines":868},{"date":"2020-8-3","action":"S","tot_orders":9,"tot_order_lines":11},{"date":"2020-8-4","action":"SM","tot_orders":286,"tot_order_lines":541},{"date":"2020-8-4","action":"DS","tot_orders":217,"tot_order_lines":1476},{"date":"2020-8-4","action":"S","tot_orders":27,"tot_order_lines":58},{"date":"2020-8-4","action":"DA","tot_orders":7,"tot_order_lines":8},{"date":"2020-8-5","action":"S","tot_orders":17,"tot_order_lines":24},{"date":"2020-8-5","action":"DA","tot_orders":5,"tot_order_lines":5},{"date":"2020-8-5","action":"SM","tot_orders":177,"tot_order_lines":595},{"date":"2020-8-5","action":"DS","tot_orders":170,"tot_order_lines":588},{"date":"2020-8-6","action":"SM","tot_orders":306,"tot_order_lines":547},{"date":"2020-8-6","action":"DS","tot_orders":174,"tot_order_lines":340},{"date":"2020-8-6","action":"DA","tot_orders":8,"tot_order_lines":8},{"date":"2020-8-6","action":"S","tot_orders":8,"tot_order_lines":9},{"date":"2020-8-7","action":"SM","tot_orders":410,"tot_order_lines":707},{"date":"2020-8-7","action":"DS","tot_orders":138,"tot_order_lines":251},{"date":"2020-8-7","action":"S","tot_orders":13,"tot_order_lines":20},{"date":"2020-8-7","action":"DA","tot_orders":9,"tot_order_lines":9},{"date":"2020-8-8","action":"SM","tot_orders":2,"tot_order_lines":2},{"date":"2020-8-10","action":"S","tot_orders":22,"tot_order_lines":25},{"date":"2020-8-10","action":"SM","tot_orders":184,"tot_order_lines":389},{"date":"2020-8-10","action":"DA","tot_orders":14,"tot_order_lines":14},{"date":"2020-8-10","action":"DS","tot_orders":266,"tot_order_lines":1750},{"date":"2020-8-11","action":"SM","tot_orders":190,"tot_order_lines":589},{"date":"2020-8-11","action":"S","tot_orders":12,"tot_order_lines":34},{"date":"2020-8-11","action":"DS","tot_orders":220,"tot_order_lines":870},{"date":"2020-8-11","action":"DA","tot_orders":8,"tot_order_lines":10},{"date":"2020-8-12","action":"DS","tot_orders":184,"tot_order_lines":537},{"date":"2020-8-12","action":"DA","tot_orders":9,"tot_order_lines":9},{"date":"2020-8-12","action":"S","tot_orders":14,"tot_order_lines":15},{"date":"2020-8-12","action":"SM","tot_orders":113,"tot_order_lines":370},{"date":"2020-8-13","action":"DA","tot_orders":5,"tot_order_lines":5},{"date":"2020-8-13","action":"S","tot_orders":14,"tot_order_lines":41},{"date":"2020-8-13","action":"DS","tot_orders":186,"tot_order_lines":594},{"date":"2020-8-13","action":"SM","tot_orders":132,"tot_order_lines":356},{"date":"2020-8-14","action":"DA","tot_orders":13,"tot_order_lines":15},{"date":"2020-8-14","action":"DS","tot_orders":134,"tot_order_lines":396},{"date":"2020-8-14","action":"SM","tot_orders":594,"tot_order_lines":992},{"date":"2020-8-14","action":"S","tot_orders":12,"tot_order_lines":17},{"date":"2020-8-15","action":"DS","tot_orders":4,"tot_order_lines":5},{"date":"2020-8-15","action":"SM","tot_orders":56,"tot_order_lines":159},{"date":"2020-8-16","action":"SM","tot_orders":8,"tot_order_lines":39},{"date":"2020-8-16","action":"DS","tot_orders":6,"tot_order_lines":6},{"date":"2020-8-17","action":"DA","tot_orders":31,"tot_order_lines":48},{"date":"2020-8-17","action":"S","tot_orders":22,"tot_order_lines":30},{"date":"2020-8-17","action":"SM","tot_orders":552,"tot_order_lines":1099},{"date":"2020-8-17","action":"DS","tot_orders":180,"tot_order_lines":1006},{"date":"2020-8-18","action":"DS","tot_orders":219,"tot_order_lines":1505},{"date":"2020-8-18","action":"DA","tot_orders":16,"tot_order_lines":16},{"date":"2020-8-18","action":"SM","tot_orders":442,"tot_order_lines":769},{"date":"2020-8-18","action":"S","tot_orders":27,"tot_order_lines":43},{"date":"2020-8-19","action":"DA","tot_orders":4,"tot_order_lines":4},{"date":"2020-8-19","action":"S","tot_orders":12,"tot_order_lines":12},{"date":"2020-8-19","action":"DS","tot_orders":183,"tot_order_lines":535},{"date":"2020-8-19","action":"SM","tot_orders":402,"tot_order_lines":714},{"date":"2020-8-20","action":"DS","tot_orders":159,"tot_order_lines":365},{"date":"2020-8-20","action":"DA","tot_orders":5,"tot_order_lines":5},{"date":"2020-8-20","action":"SM","tot_orders":116,"tot_order_lines":291},{"date":"2020-8-20","action":"S","tot_orders":10,"tot_order_lines":15},{"date":"2020-8-21","action":"DA","tot_orders":2,"tot_order_lines":2},{"date":"2020-8-21","action":"SM","tot_orders":87,"tot_order_lines":271},{"date":"2020-8-21","action":"DS","tot_orders":86,"tot_order_lines":322},{"date":"2020-8-21","action":"S","tot_orders":6,"tot_order_lines":33},{"date":"2020-8-22","action":"SM","tot_orders":3,"tot_order_lines":3},{"date":"2020-8-23","action":"SM","tot_orders":12,"tot_order_lines":14},{"date":"2020-8-23","action":"DS","tot_orders":2,"tot_order_lines":3},{"date":"2020-8-24","action":"DA","tot_orders":8,"tot_order_lines":8},{"date":"2020-8-24","action":"DS","tot_orders":215,"tot_order_lines":1063},{"date":"2020-8-24","action":"SM","tot_orders":119,"tot_order_lines":352},{"date":"2020-8-24","action":"S","tot_orders":9,"tot_order_lines":12},{"date":"2020-8-25","action":"DA","tot_orders":15,"tot_order_lines":18},{"date":"2020-8-25","action":"DS","tot_orders":239,"tot_order_lines":1303},{"date":"2020-8-25","action":"S","tot_orders":13,"tot_order_lines":19},{"date":"2020-8-25","action":"SM","tot_orders":201,"tot_order_lines":469},{"date":"2020-8-26","action":"DS","tot_orders":223,"tot_order_lines":846},{"date":"2020-8-26","action":"S","tot_orders":15,"tot_order_lines":35},{"date":"2020-8-26","action":"DA","tot_orders":10,"tot_order_lines":11},{"date":"2020-8-26","action":"SM","tot_orders":98,"tot_order_lines":349},{"date":"2020-8-27","action":"SM","tot_orders":93,"tot_order_lines":296},{"date":"2020-8-27","action":"DS","tot_orders":142,"tot_order_lines":363},{"date":"2020-8-27","action":"S","tot_orders":19,"tot_order_lines":53},{"date":"2020-8-27","action":"DA","tot_orders":11,"tot_order_lines":11},{"date":"2020-8-28","action":"DS","tot_orders":118,"tot_order_lines":327},{"date":"2020-8-28","action":"DA","tot_orders":12,"tot_order_lines":12},{"date":"2020-8-28","action":"SM","tot_orders":38,"tot_order_lines":106},{"date":"2020-8-28","action":"S","tot_orders":1,"tot_order_lines":1},{"date":"2020-8-29","action":"SM","tot_orders":2,"tot_order_lines":16},{"date":"2020-8-31","action":"SM","tot_orders":146,"tot_order_lines":530},{"date":"2020-8-31","action":"S","tot_orders":19,"tot_order_lines":40},{"date":"2020-8-31","action":"DS","tot_orders":259,"tot_order_lines":1562},{"date":"2020-8-31","action":"DA","tot_orders":8,"tot_order_lines":9},{"date":"2020-9-1","action":"DS","tot_orders":247,"tot_order_lines":1147},{"date":"2020-9-1","action":"DA","tot_orders":6,"tot_order_lines":6},{"date":"2020-9-1","action":"SM","tot_orders":133,"tot_order_lines":240},{"date":"2020-9-1","action":"S","tot_orders":26,"tot_order_lines":115},{"date":"2020-9-2","action":"DA","tot_orders":3,"tot_order_lines":8},{"date":"2020-9-2","action":"DS","tot_orders":203,"tot_order_lines":560},{"date":"2020-9-2","action":"SM","tot_orders":102,"tot_order_lines":273},{"date":"2020-9-2","action":"S","tot_orders":22,"tot_order_lines":280},{"date":"2020-9-3","action":"DA","tot_orders":5,"tot_order_lines":5},{"date":"2020-9-3","action":"SM","tot_orders":119,"tot_order_lines":286},{"date":"2020-9-3","action":"DS","tot_orders":162,"tot_order_lines":638},{"date":"2020-9-3","action":"S","tot_orders":21,"tot_order_lines":34},{"date":"2020-9-4","action":"SM","tot_orders":42,"tot_order_lines":88},{"date":"2020-9-4","action":"S","tot_orders":7,"tot_order_lines":48},{"date":"2020-9-4","action":"DS","tot_orders":93,"tot_order_lines":317},{"date":"2020-9-4","action":"DA","tot_orders":4,"tot_order_lines":4},{"date":"2020-9-7","action":"DS","tot_orders":2,"tot_order_lines":3},{"date":"2020-9-8","action":"SM","tot_orders":136,"tot_order_lines":282},{"date":"2020-9-8","action":"DS","tot_orders":264,"tot_order_lines":1616},{"date":"2020-9-8","action":"S","tot_orders":13,"tot_order_lines":19},{"date":"2020-9-8","action":"DA","tot_orders":11,"tot_order_lines":11},{"date":"2020-9-9","action":"DS","tot_orders":245,"tot_order_lines":721},{"date":"2020-9-9","action":"SM","tot_orders":144,"tot_order_lines":386},{"date":"2020-9-9","action":"S","tot_orders":12,"tot_order_lines":33},{"date":"2020-9-9","action":"DA","tot_orders":5,"tot_order_lines":5},{"date":"2020-9-10","action":"S","tot_orders":21,"tot_order_lines":65},{"date":"2020-9-10","action":"DS","tot_orders":290,"tot_order_lines":769},{"date":"2020-9-10","action":"DA","tot_orders":8,"tot_order_lines":10},{"date":"2020-9-10","action":"SM","tot_orders":154,"tot_order_lines":373},{"date":"2020-9-11","action":"S","tot_orders":17,"tot_order_lines":37},{"date":"2020-9-11","action":"DS","tot_orders":153,"tot_order_lines":381},{"date":"2020-9-11","action":"DA","tot_orders":8,"tot_order_lines":8},{"date":"2020-9-11","action":"SM","tot_orders":103,"tot_order_lines":208},{"date":"2020-9-12","action":"DS","tot_orders":2,"tot_order_lines":2},{"date":"2020-9-13","action":"DS","tot_orders":3,"tot_order_lines":5},{"date":"2020-9-13","action":"SM","tot_orders":1,"tot_order_lines":2},{"date":"2020-9-13","action":"S","tot_orders":1,"tot_order_lines":1},{"date":"2020-9-13","action":"DA","tot_orders":1,"tot_order_lines":1},{"date":"2020-9-14","action":"DA","tot_orders":15,"tot_order_lines":22},{"date":"2020-9-14","action":"SM","tot_orders":118,"tot_order_lines":338},{"date":"2020-9-14","action":"DS","tot_orders":269,"tot_order_lines":1303},{"date":"2020-9-14","action":"S","tot_orders":18,"tot_order_lines":28},{"date":"2020-9-15","action":"DS","tot_orders":228,"tot_order_lines":1207},{"date":"2020-9-15","action":"SM","tot_orders":117,"tot_order_lines":288},{"date":"2020-9-15","action":"S","tot_orders":16,"tot_order_lines":19},{"date":"2020-9-15","action":"DA","tot_orders":4,"tot_order_lines":4},{"date":"2020-9-16","action":"DS","tot_orders":163,"tot_order_lines":448},{"date":"2020-9-16","action":"SM","tot_orders":110,"tot_order_lines":521},{"date":"2020-9-16","action":"S","tot_orders":14,"tot_order_lines":41},{"date":"2020-9-16","action":"DA","tot_orders":5,"tot_order_lines":5},{"date":"2020-9-17","action":"SM","tot_orders":113,"tot_order_lines":285},{"date":"2020-9-17","action":"DS","tot_orders":234,"tot_order_lines":582},{"date":"2020-9-17","action":"S","tot_orders":17,"tot_order_lines":55},{"date":"2020-9-17","action":"DA","tot_orders":14,"tot_order_lines":15},{"date":"2020-9-18","action":"DS","tot_orders":164,"tot_order_lines":340},{"date":"2020-9-18","action":"DA","tot_orders":4,"tot_order_lines":4},{"date":"2020-9-18","action":"S","tot_orders":17,"tot_order_lines":31},{"date":"2020-9-18","action":"SM","tot_orders":101,"tot_order_lines":359},{"date":"2020-9-20","action":"DS","tot_orders":3,"tot_order_lines":50},{"date":"2020-9-21","action":"DA","tot_orders":10,"tot_order_lines":16},{"date":"2020-9-21","action":"DS","tot_orders":224,"tot_order_lines":884},{"date":"2020-9-21","action":"SM","tot_orders":103,"tot_order_lines":252},{"date":"2020-9-21","action":"S","tot_orders":10,"tot_order_lines":38},{"date":"2020-9-22","action":"DA","tot_orders":11,"tot_order_lines":11},{"date":"2020-9-22","action":"S","tot_orders":21,"tot_order_lines":55},{"date":"2020-9-22","action":"DS","tot_orders":244,"tot_order_lines":1830},{"date":"2020-9-22","action":"SM","tot_orders":153,"tot_order_lines":341},{"date":"2020-9-23","action":"SM","tot_orders":120,"tot_order_lines":414},{"date":"2020-9-23","action":"DS","tot_orders":305,"tot_order_lines":737},{"date":"2020-9-23","action":"DA","tot_orders":8,"tot_order_lines":11},{"date":"2020-9-23","action":"S","tot_orders":15,"tot_order_lines":33},{"date":"2020-9-24","action":"SM","tot_orders":77,"tot_order_lines":256},{"date":"2020-9-24","action":"S","tot_orders":4,"tot_order_lines":34},{"date":"2020-9-24","action":"DA","tot_orders":2,"tot_order_lines":2},{"date":"2020-9-24","action":"DS","tot_orders":178,"tot_order_lines":489},{"date":"2020-9-25","action":"S","tot_orders":43,"tot_order_lines":56},{"date":"2020-9-25","action":"DS","tot_orders":165,"tot_order_lines":355},{"date":"2020-9-25","action":"SM","tot_orders":57,"tot_order_lines":208},{"date":"2020-9-25","action":"DA","tot_orders":15,"tot_order_lines":15},{"date":"2020-9-26","action":"SM","tot_orders":1,"tot_order_lines":1},{"date":"2020-9-26","action":"DS","tot_orders":1,"tot_order_lines":10},{"date":"2020-9-28","action":"S","tot_orders":18,"tot_order_lines":23},{"date":"2020-9-28","action":"SM","tot_orders":96,"tot_order_lines":289},{"date":"2020-9-28","action":"DS","tot_orders":241,"tot_order_lines":820},{"date":"2020-9-28","action":"DA","tot_orders":4,"tot_order_lines":4},{"date":"2020-9-29","action":"DA","tot_orders":15,"tot_order_lines":19},{"date":"2020-9-29","action":"DS","tot_orders":264,"tot_order_lines":1172},{"date":"2020-9-29","action":"S","tot_orders":21,"tot_order_lines":140},{"date":"2020-9-29","action":"SM","tot_orders":123,"tot_order_lines":401},{"date":"2020-9-30","action":"DA","tot_orders":5,"tot_order_lines":5},{"date":"2020-9-30","action":"S","tot_orders":16,"tot_order_lines":54},{"date":"2020-9-30","action":"DS","tot_orders":171,"tot_order_lines":496},{"date":"2020-9-30","action":"SM","tot_orders":77,"tot_order_lines":210},{"date":"2020-10-1","action":"DS","tot_orders":174,"tot_order_lines":444},{"date":"2020-10-1","action":"SM","tot_orders":95,"tot_order_lines":249},{"date":"2020-10-1","action":"S","tot_orders":29,"tot_order_lines":134},{"date":"2020-10-1","action":"DA","tot_orders":25,"tot_order_lines":28},{"date":"2020-10-2","action":"DS","tot_orders":153,"tot_order_lines":377},{"date":"2020-10-2","action":"S","tot_orders":8,"tot_order_lines":9},{"date":"2020-10-2","action":"SM","tot_orders":89,"tot_order_lines":192},{"date":"2020-10-2","action":"DA","tot_orders":6,"tot_order_lines":8},{"date":"2020-10-3","action":"DS","tot_orders":3,"tot_order_lines":3},{"date":"2020-10-3","action":"SM","tot_orders":1,"tot_order_lines":1},{"date":"2020-10-4","action":"DS","tot_orders":2,"tot_order_lines":2},{"date":"2020-10-5","action":"S","tot_orders":15,"tot_order_lines":25},{"date":"2020-10-5","action":"DA","tot_orders":11,"tot_order_lines":12},{"date":"2020-10-5","action":"DS","tot_orders":218,"tot_order_lines":1198},{"date":"2020-10-5","action":"SM","tot_orders":131,"tot_order_lines":295},{"date":"2020-10-6","action":"SM","tot_orders":152,"tot_order_lines":396},{"date":"2020-10-6","action":"S","tot_orders":15,"tot_order_lines":51},{"date":"2020-10-6","action":"DA","tot_orders":4,"tot_order_lines":4},{"date":"2020-10-6","action":"DS","tot_orders":211,"tot_order_lines":891},{"date":"2020-10-7","action":"DA","tot_orders":10,"tot_order_lines":10},{"date":"2020-10-7","action":"SM","tot_orders":115,"tot_order_lines":353},{"date":"2020-10-7","action":"S","tot_orders":10,"tot_order_lines":41},{"date":"2020-10-7","action":"DS","tot_orders":226,"tot_order_lines":667},{"date":"2020-10-8","action":"DS","tot_orders":215,"tot_order_lines":656},{"date":"2020-10-8","action":"S","tot_orders":5,"tot_order_lines":23},{"date":"2020-10-8","action":"DA","tot_orders":17,"tot_order_lines":19},{"date":"2020-10-8","action":"SM","tot_orders":108,"tot_order_lines":302},{"date":"2020-10-9","action":"SM","tot_orders":122,"tot_order_lines":297},{"date":"2020-10-9","action":"DS","tot_orders":121,"tot_order_lines":322},{"date":"2020-10-9","action":"S","tot_orders":25,"tot_order_lines":48},{"date":"2020-10-9","action":"DA","tot_orders":8,"tot_order_lines":15},{"date":"2020-10-10","action":"SM","tot_orders":1,"tot_order_lines":1},{"date":"2020-10-10","action":"DS","tot_orders":7,"tot_order_lines":7},{"date":"2020-10-11","action":"DS","tot_orders":1,"tot_order_lines":1},{"date":"2020-10-11","action":"SM","tot_orders":4,"tot_order_lines":29},{"date":"2020-10-12","action":"SM","tot_orders":122,"tot_order_lines":360},{"date":"2020-10-12","action":"DA","tot_orders":13,"tot_order_lines":13},{"date":"2020-10-12","action":"DS","tot_orders":207,"tot_order_lines":1027},{"date":"2020-10-12","action":"S","tot_orders":18,"tot_order_lines":43},{"date":"2020-10-13","action":"SM","tot_orders":205,"tot_order_lines":426},{"date":"2020-10-13","action":"DA","tot_orders":4,"tot_order_lines":5},{"date":"2020-10-13","action":"S","tot_orders":20,"tot_order_lines":36},{"date":"2020-10-13","action":"DS","tot_orders":348,"tot_order_lines":1221},{"date":"2020-10-14","action":"DS","tot_orders":199,"tot_order_lines":416},{"date":"2020-10-14","action":"S","tot_orders":18,"tot_order_lines":85},{"date":"2020-10-14","action":"DA","tot_orders":10,"tot_order_lines":10},{"date":"2020-10-14","action":"SM","tot_orders":117,"tot_order_lines":441},{"date":"2020-10-15","action":"SM","tot_orders":99,"tot_order_lines":250},{"date":"2020-10-15","action":"DS","tot_orders":248,"tot_order_lines":581},{"date":"2020-10-15","action":"S","tot_orders":14,"tot_order_lines":68},{"date":"2020-10-15","action":"DA","tot_orders":18,"tot_order_lines":18},{"date":"2020-10-16","action":"SM","tot_orders":74,"tot_order_lines":136},{"date":"2020-10-16","action":"S","tot_orders":16,"tot_order_lines":80},{"date":"2020-10-16","action":"DA","tot_orders":3,"tot_order_lines":4},{"date":"2020-10-16","action":"DS","tot_orders":101,"tot_order_lines":189},{"date":"2020-10-17","action":"DS","tot_orders":1,"tot_order_lines":1},{"date":"2020-10-18","action":"S","tot_orders":1,"tot_order_lines":13},{"date":"2020-10-18","action":"SM","tot_orders":1,"tot_order_lines":4},{"date":"2020-10-19","action":"SM","tot_orders":88,"tot_order_lines":236},{"date":"2020-10-19","action":"DS","tot_orders":212,"tot_order_lines":1028},{"date":"2020-10-19","action":"DA","tot_orders":5,"tot_order_lines":5},{"date":"2020-10-19","action":"S","tot_orders":17,"tot_order_lines":51},{"date":"2020-10-20","action":"S","tot_orders":28,"tot_order_lines":150},{"date":"2020-10-20","action":"DS","tot_orders":271,"tot_order_lines":1128},{"date":"2020-10-20","action":"DA","tot_orders":11,"tot_order_lines":13},{"date":"2020-10-20","action":"SM","tot_orders":164,"tot_order_lines":364},{"date":"2020-10-21","action":"S","tot_orders":16,"tot_order_lines":33},{"date":"2020-10-21","action":"DS","tot_orders":185,"tot_order_lines":459},{"date":"2020-10-21","action":"DA","tot_orders":9,"tot_order_lines":11},{"date":"2020-10-21","action":"SM","tot_orders":116,"tot_order_lines":330},{"date":"2020-10-22","action":"SM","tot_orders":93,"tot_order_lines":154},{"date":"2020-10-22","action":"DA","tot_orders":5,"tot_order_lines":6},{"date":"2020-10-22","action":"DS","tot_orders":213,"tot_order_lines":541},{"date":"2020-10-22","action":"S","tot_orders":11,"tot_order_lines":19},{"date":"2020-10-23","action":"DA","tot_orders":20,"tot_order_lines":20},{"date":"2020-10-23","action":"DS","tot_orders":122,"tot_order_lines":369},{"date":"2020-10-23","action":"S","tot_orders":10,"tot_order_lines":38},{"date":"2020-10-23","action":"SM","tot_orders":65,"tot_order_lines":84},{"date":"2020-10-24","action":"S","tot_orders":1,"tot_order_lines":1},{"date":"2020-10-24","action":"DS","tot_orders":27,"tot_order_lines":32},{"date":"2020-10-25","action":"SM","tot_orders":1,"tot_order_lines":1},{"date":"2020-10-26","action":"S","tot_orders":18,"tot_order_lines":20},{"date":"2020-10-26","action":"DA","tot_orders":9,"tot_order_lines":12},{"date":"2020-10-26","action":"SM","tot_orders":123,"tot_order_lines":380},{"date":"2020-10-26","action":"DS","tot_orders":216,"tot_order_lines":1399},{"date":"2020-10-27","action":"S","tot_orders":14,"tot_order_lines":44},{"date":"2020-10-27","action":"SM","tot_orders":143,"tot_order_lines":420},{"date":"2020-10-27","action":"DS","tot_orders":209,"tot_order_lines":662},{"date":"2020-10-27","action":"DA","tot_orders":6,"tot_order_lines":6},{"date":"2020-10-28","action":"DS","tot_orders":195,"tot_order_lines":629},{"date":"2020-10-28","action":"DA","tot_orders":3,"tot_order_lines":3},{"date":"2020-10-28","action":"SM","tot_orders":93,"tot_order_lines":218},{"date":"2020-10-28","action":"S","tot_orders":16,"tot_order_lines":18},{"date":"2020-10-29","action":"DA","tot_orders":9,"tot_order_lines":9},{"date":"2020-10-29","action":"SM","tot_orders":82,"tot_order_lines":147},{"date":"2020-10-29","action":"S","tot_orders":25,"tot_order_lines":93},{"date":"2020-10-29","action":"DS","tot_orders":170,"tot_order_lines":391},{"date":"2020-10-30","action":"DA","tot_orders":4,"tot_order_lines":5},{"date":"2020-10-30","action":"DS","tot_orders":82,"tot_order_lines":212},{"date":"2020-10-30","action":"S","tot_orders":12,"tot_order_lines":16},{"date":"2020-10-30","action":"SM","tot_orders":65,"tot_order_lines":120},{"date":"2020-11-1","action":"DS","tot_orders":3,"tot_order_lines":4},{"date":"2020-11-2","action":"DS","tot_orders":228,"tot_order_lines":1015},{"date":"2020-11-2","action":"SM","tot_orders":94,"tot_order_lines":259},{"date":"2020-11-2","action":"S","tot_orders":19,"tot_order_lines":29},{"date":"2020-11-2","action":"DA","tot_orders":6,"tot_order_lines":6},{"date":"2020-11-3","action":"SM","tot_orders":116,"tot_order_lines":277},{"date":"2020-11-3","action":"S","tot_orders":22,"tot_order_lines":51},{"date":"2020-11-3","action":"DS","tot_orders":239,"tot_order_lines":907},{"date":"2020-11-3","action":"DA","tot_orders":6,"tot_order_lines":6},{"date":"2020-11-4","action":"DS","tot_orders":183,"tot_order_lines":627},{"date":"2020-11-4","action":"DA","tot_orders":13,"tot_order_lines":13},{"date":"2020-11-4","action":"S","tot_orders":28,"tot_order_lines":53},{"date":"2020-11-4","action":"SM","tot_orders":121,"tot_order_lines":242},{"date":"2020-11-5","action":"DS","tot_orders":117,"tot_order_lines":408},{"date":"2020-11-5","action":"SM","tot_orders":74,"tot_order_lines":138},{"date":"2020-11-5","action":"S","tot_orders":7,"tot_order_lines":8},{"date":"2020-11-5","action":"DA","tot_orders":6,"tot_order_lines":8},{"date":"2020-11-6","action":"S","tot_orders":6,"tot_order_lines":9},{"date":"2020-11-6","action":"DS","tot_orders":129,"tot_order_lines":369},{"date":"2020-11-6","action":"SM","tot_orders":1188,"tot_order_lines":1251},{"date":"2020-11-7","action":"SM","tot_orders":2,"tot_order_lines":2},{"date":"2020-11-9","action":"S","tot_orders":14,"tot_order_lines":45},{"date":"2020-11-9","action":"SM","tot_orders":93,"tot_order_lines":321},{"date":"2020-11-9","action":"DS","tot_orders":262,"tot_order_lines":1363},{"date":"2020-11-9","action":"DA","tot_orders":8,"tot_order_lines":11},{"date":"2020-11-10","action":"DS","tot_orders":335,"tot_order_lines":872},{"date":"2020-11-10","action":"SM","tot_orders":87,"tot_order_lines":245},{"date":"2020-11-10","action":"S","tot_orders":13,"tot_order_lines":39},{"date":"2020-11-10","action":"DA","tot_orders":3,"tot_order_lines":3},{"date":"2020-11-11","action":"DA","tot_orders":6,"tot_order_lines":6},{"date":"2020-11-11","action":"DS","tot_orders":132,"tot_order_lines":299},{"date":"2020-11-11","action":"SM","tot_orders":81,"tot_order_lines":196},{"date":"2020-11-11","action":"S","tot_orders":4,"tot_order_lines":18},{"date":"2020-11-12","action":"DA","tot_orders":3,"tot_order_lines":3},{"date":"2020-11-12","action":"S","tot_orders":12,"tot_order_lines":27},{"date":"2020-11-12","action":"SM","tot_orders":71,"tot_order_lines":188},{"date":"2020-11-12","action":"DS","tot_orders":132,"tot_order_lines":330},{"date":"2020-11-13","action":"S","tot_orders":11,"tot_order_lines":42},{"date":"2020-11-13","action":"DS","tot_orders":97,"tot_order_lines":290},{"date":"2020-11-13","action":"DA","tot_orders":7,"tot_order_lines":7},{"date":"2020-11-13","action":"SM","tot_orders":63,"tot_order_lines":118},{"date":"2020-11-16","action":"SM","tot_orders":100,"tot_order_lines":320},{"date":"2020-11-16","action":"S","tot_orders":9,"tot_order_lines":11},{"date":"2020-11-16","action":"DA","tot_orders":4,"tot_order_lines":4},{"date":"2020-11-16","action":"DS","tot_orders":218,"tot_order_lines":1390},{"date":"2020-11-17","action":"SM","tot_orders":76,"tot_order_lines":230},{"date":"2020-11-17","action":"DA","tot_orders":8,"tot_order_lines":9},{"date":"2020-11-17","action":"S","tot_orders":6,"tot_order_lines":12},{"date":"2020-11-17","action":"DS","tot_orders":206,"tot_order_lines":516},{"date":"2020-11-18","action":"SM","tot_orders":65,"tot_order_lines":117},{"date":"2020-11-18","action":"DS","tot_orders":180,"tot_order_lines":308},{"date":"2020-11-18","action":"DA","tot_orders":10,"tot_order_lines":12},{"date":"2020-11-18","action":"S","tot_orders":5,"tot_order_lines":14},{"date":"2020-11-19","action":"DS","tot_orders":136,"tot_order_lines":459},{"date":"2020-11-19","action":"DA","tot_orders":4,"tot_order_lines":4},{"date":"2020-11-19","action":"S","tot_orders":3,"tot_order_lines":3},{"date":"2020-11-19","action":"SM","tot_orders":74,"tot_order_lines":160},{"date":"2020-11-20","action":"SM","tot_orders":56,"tot_order_lines":108},{"date":"2020-11-20","action":"S","tot_orders":10,"tot_order_lines":13},{"date":"2020-11-20","action":"DS","tot_orders":91,"tot_order_lines":203},{"date":"2020-11-20","action":"DA","tot_orders":5,"tot_order_lines":5},{"date":"2020-11-23","action":"S","tot_orders":13,"tot_order_lines":16},{"date":"2020-11-23","action":"DS","tot_orders":236,"tot_order_lines":1301},{"date":"2020-11-23","action":"SM","tot_orders":118,"tot_order_lines":276},{"date":"2020-11-23","action":"DA","tot_orders":3,"tot_order_lines":3},{"date":"2020-11-24","action":"DS","tot_orders":280,"tot_order_lines":1332},{"date":"2020-11-24","action":"SM","tot_orders":82,"tot_order_lines":176},{"date":"2020-11-24","action":"S","tot_orders":2,"tot_order_lines":2},{"date":"2020-11-24","action":"DA","tot_orders":8,"tot_order_lines":10},{"date":"2020-11-25","action":"DS","tot_orders":115,"tot_order_lines":172},{"date":"2020-11-25","action":"SM","tot_orders":40,"tot_order_lines":59},{"date":"2020-11-25","action":"DA","tot_orders":3,"tot_order_lines":3},{"date":"2020-11-25","action":"S","tot_orders":5,"tot_order_lines":7},{"date":"2020-11-27","action":"S","tot_orders":2,"tot_order_lines":3},{"date":"2020-11-27","action":"SM","tot_orders":15,"tot_order_lines":17},{"date":"2020-11-27","action":"DS","tot_orders":26,"tot_order_lines":87},{"date":"2020-11-28","action":"SM","tot_orders":1,"tot_order_lines":1},{"date":"2020-11-29","action":"SM","tot_orders":3,"tot_order_lines":4},{"date":"2020-11-29","action":"DS","tot_orders":4,"tot_order_lines":5},{"date":"2020-11-29","action":"S","tot_orders":3,"tot_order_lines":4},{"date":"2020-11-30","action":"SM","tot_orders":88,"tot_order_lines":207},{"date":"2020-11-30","action":"DA","tot_orders":5,"tot_order_lines":5},{"date":"2020-11-30","action":"S","tot_orders":6,"tot_order_lines":6},{"date":"2020-11-30","action":"DS","tot_orders":233,"tot_order_lines":1273},{"date":"2020-12-1","action":"DA","tot_orders":1,"tot_order_lines":1},{"date":"2020-12-1","action":"DS","tot_orders":193,"tot_order_lines":825},{"date":"2020-12-1","action":"S","tot_orders":21,"tot_order_lines":112},{"date":"2020-12-1","action":"SM","tot_orders":88,"tot_order_lines":254},{"date":"2020-12-2","action":"DS","tot_orders":186,"tot_order_lines":598},{"date":"2020-12-2","action":"S","tot_orders":17,"tot_order_lines":25},{"date":"2020-12-2","action":"DA","tot_orders":3,"tot_order_lines":4},{"date":"2020-12-2","action":"SM","tot_orders":48,"tot_order_lines":89},{"date":"2020-12-3","action":"S","tot_orders":9,"tot_order_lines":9},{"date":"2020-12-3","action":"SM","tot_orders":56,"tot_order_lines":123},{"date":"2020-12-3","action":"DA","tot_orders":6,"tot_order_lines":7},{"date":"2020-12-3","action":"DS","tot_orders":186,"tot_order_lines":535},{"date":"2020-12-4","action":"DA","tot_orders":1,"tot_order_lines":1},{"date":"2020-12-4","action":"SM","tot_orders":68,"tot_order_lines":141},{"date":"2020-12-4","action":"S","tot_orders":29,"tot_order_lines":29},{"date":"2020-12-4","action":"DS","tot_orders":102,"tot_order_lines":405},{"date":"2020-12-7","action":"S","tot_orders":9,"tot_order_lines":14},{"date":"2020-12-7","action":"DS","tot_orders":191,"tot_order_lines":999},{"date":"2020-12-7","action":"SM","tot_orders":69,"tot_order_lines":247},{"date":"2020-12-7","action":"DA","tot_orders":7,"tot_order_lines":7},{"date":"2020-12-8","action":"DA","tot_orders":3,"tot_order_lines":3},{"date":"2020-12-8","action":"S","tot_orders":6,"tot_order_lines":9},{"date":"2020-12-8","action":"SM","tot_orders":79,"tot_order_lines":228},{"date":"2020-12-8","action":"DS","tot_orders":210,"tot_order_lines":833},{"date":"2020-12-9","action":"DA","tot_orders":2,"tot_order_lines":2},{"date":"2020-12-9","action":"SM","tot_orders":60,"tot_order_lines":98},{"date":"2020-12-9","action":"DS","tot_orders":146,"tot_order_lines":405},{"date":"2020-12-9","action":"S","tot_orders":1,"tot_order_lines":1},{"date":"2020-12-10","action":"SM","tot_orders":86,"tot_order_lines":127},{"date":"2020-12-10","action":"DA","tot_orders":7,"tot_order_lines":7},{"date":"2020-12-10","action":"S","tot_orders":8,"tot_order_lines":8},{"date":"2020-12-10","action":"DS","tot_orders":146,"tot_order_lines":289},{"date":"2020-12-11","action":"S","tot_orders":2,"tot_order_lines":2},{"date":"2020-12-11","action":"DS","tot_orders":94,"tot_order_lines":214},{"date":"2020-12-11","action":"SM","tot_orders":49,"tot_order_lines":64},{"date":"2020-12-12","action":"SM","tot_orders":3,"tot_order_lines":11},{"date":"2020-12-12","action":"S","tot_orders":1,"tot_order_lines":1},{"date":"2020-12-13","action":"DS","tot_orders":7,"tot_order_lines":22},{"date":"2020-12-13","action":"SM","tot_orders":1,"tot_order_lines":2},{"date":"2020-12-14","action":"DA","tot_orders":5,"tot_order_lines":5},{"date":"2020-12-14","action":"SM","tot_orders":96,"tot_order_lines":295},{"date":"2020-12-14","action":"S","tot_orders":8,"tot_order_lines":19},{"date":"2020-12-14","action":"DS","tot_orders":235,"tot_order_lines":1210},{"date":"2020-12-15","action":"DS","tot_orders":194,"tot_order_lines":720},{"date":"2020-12-15","action":"S","tot_orders":13,"tot_order_lines":13},{"date":"2020-12-15","action":"DA","tot_orders":8,"tot_order_lines":8},{"date":"2020-12-15","action":"SM","tot_orders":95,"tot_order_lines":217},{"date":"2020-12-16","action":"DS","tot_orders":142,"tot_order_lines":295},{"date":"2020-12-16","action":"DA","tot_orders":13,"tot_order_lines":13},{"date":"2020-12-16","action":"S","tot_orders":15,"tot_order_lines":55},{"date":"2020-12-16","action":"SM","tot_orders":51,"tot_order_lines":130},{"date":"2020-12-17","action":"S","tot_orders":6,"tot_order_lines":26},{"date":"2020-12-17","action":"DS","tot_orders":177,"tot_order_lines":523},{"date":"2020-12-17","action":"SM","tot_orders":78,"tot_order_lines":125},{"date":"2020-12-17","action":"DA","tot_orders":4,"tot_order_lines":4},{"date":"2020-12-18","action":"S","tot_orders":3,"tot_order_lines":9},{"date":"2020-12-18","action":"DS","tot_orders":146,"tot_order_lines":291},{"date":"2020-12-18","action":"DA","tot_orders":6,"tot_order_lines":6},{"date":"2020-12-18","action":"SM","tot_orders":39,"tot_order_lines":103},{"date":"2020-12-19","action":"DS","tot_orders":3,"tot_order_lines":7},{"date":"2020-12-19","action":"SM","tot_orders":4,"tot_order_lines":10},{"date":"2020-12-21","action":"SM","tot_orders":75,"tot_order_lines":330},{"date":"2020-12-21","action":"S","tot_orders":16,"tot_order_lines":49},{"date":"2020-12-21","action":"DS","tot_orders":243,"tot_order_lines":1192},{"date":"2020-12-21","action":"DA","tot_orders":12,"tot_order_lines":12},{"date":"2020-12-22","action":"DA","tot_orders":2,"tot_order_lines":2},{"date":"2020-12-22","action":"SM","tot_orders":56,"tot_order_lines":294},{"date":"2020-12-22","action":"DS","tot_orders":113,"tot_order_lines":477},{"date":"2020-12-22","action":"S","tot_orders":8,"tot_order_lines":25},{"date":"2020-12-23","action":"DS","tot_orders":65,"tot_order_lines":162},{"date":"2020-12-23","action":"DA","tot_orders":5,"tot_order_lines":5},{"date":"2020-12-23","action":"S","tot_orders":25,"tot_order_lines":51},{"date":"2020-12-23","action":"SM","tot_orders":22,"tot_order_lines":72},{"date":"2020-12-24","action":"SM","tot_orders":1,"tot_order_lines":1},{"date":"2020-12-26","action":"S","tot_orders":1,"tot_order_lines":17},{"date":"2020-12-26","action":"DS","tot_orders":1,"tot_order_lines":12},{"date":"2020-12-27","action":"S","tot_orders":7,"tot_order_lines":57},{"date":"2020-12-28","action":"S","tot_orders":13,"tot_order_lines":13},{"date":"2020-12-28","action":"SM","tot_orders":51,"tot_order_lines":112},{"date":"2020-12-28","action":"DS","tot_orders":88,"tot_order_lines":455},{"date":"2020-12-29","action":"DA","tot_orders":2,"tot_order_lines":2},{"date":"2020-12-29","action":"DS","tot_orders":72,"tot_order_lines":303},{"date":"2020-12-29","action":"SM","tot_orders":28,"tot_order_lines":123},{"date":"2020-12-29","action":"S","tot_orders":9,"tot_order_lines":10},{"date":"2020-12-30","action":"DS","tot_orders":43,"tot_order_lines":189},{"date":"2020-12-30","action":"SM","tot_orders":15,"tot_order_lines":74},{"date":"2020-12-30","action":"S","tot_orders":1,"tot_order_lines":1},{"date":"2020-12-31","action":"SM","tot_orders":5,"tot_order_lines":6},{"date":"2021-1-1","action":"SM","tot_orders":1,"tot_order_lines":1},{"date":"2021-1-3","action":"DS","tot_orders":2,"tot_order_lines":3},{"date":"2021-1-4","action":"DS","tot_orders":234,"tot_order_lines":1341},{"date":"2021-1-4","action":"S","tot_orders":11,"tot_order_lines":12},{"date":"2021-1-4","action":"SM","tot_orders":79,"tot_order_lines":236},{"date":"2021-1-4","action":"DA","tot_orders":17,"tot_order_lines":18},{"date":"2021-1-5","action":"SM","tot_orders":87,"tot_order_lines":264},{"date":"2021-1-5","action":"S","tot_orders":10,"tot_order_lines":27},{"date":"2021-1-5","action":"DS","tot_orders":210,"tot_order_lines":938},{"date":"2021-1-5","action":"DA","tot_orders":5,"tot_order_lines":6},{"date":"2021-1-6","action":"S","tot_orders":8,"tot_order_lines":31},{"date":"2021-1-6","action":"DA","tot_orders":3,"tot_order_lines":4},{"date":"2021-1-6","action":"DS","tot_orders":183,"tot_order_lines":324},{"date":"2021-1-6","action":"SM","tot_orders":80,"tot_order_lines":122},{"date":"2021-1-7","action":"SM","tot_orders":97,"tot_order_lines":186},{"date":"2021-1-7","action":"DS","tot_orders":98,"tot_order_lines":253},{"date":"2021-1-7","action":"S","tot_orders":12,"tot_order_lines":22},{"date":"2021-1-7","action":"DA","tot_orders":4,"tot_order_lines":4},{"date":"2021-1-8","action":"SM","tot_orders":65,"tot_order_lines":107},{"date":"2021-1-8","action":"S","tot_orders":3,"tot_order_lines":4},{"date":"2021-1-8","action":"DA","tot_orders":1,"tot_order_lines":1},{"date":"2021-1-8","action":"DS","tot_orders":120,"tot_order_lines":369},{"date":"2021-1-9","action":"SM","tot_orders":1,"tot_order_lines":1},{"date":"2021-1-9","action":"DS","tot_orders":2,"tot_order_lines":10},{"date":"2021-1-9","action":"S","tot_orders":1,"tot_order_lines":3},{"date":"2021-1-11","action":"S","tot_orders":9,"tot_order_lines":12},{"date":"2021-1-11","action":"DA","tot_orders":7,"tot_order_lines":8},{"date":"2021-1-11","action":"SM","tot_orders":117,"tot_order_lines":319},{"date":"2021-1-11","action":"DS","tot_orders":265,"tot_order_lines":1274},{"date":"2021-1-12","action":"S","tot_orders":15,"tot_order_lines":18},{"date":"2021-1-12","action":"DS","tot_orders":229,"tot_order_lines":827},{"date":"2021-1-12","action":"DA","tot_orders":3,"tot_order_lines":3},{"date":"2021-1-12","action":"SM","tot_orders":117,"tot_order_lines":255},{"date":"2021-1-13","action":"S","tot_orders":44,"tot_order_lines":52},{"date":"2021-1-13","action":"DA","tot_orders":10,"tot_order_lines":10},{"date":"2021-1-13","action":"DS","tot_orders":159,"tot_order_lines":456},{"date":"2021-1-13","action":"SM","tot_orders":98,"tot_order_lines":209},{"date":"2021-1-14","action":"DS","tot_orders":239,"tot_order_lines":588},{"date":"2021-1-14","action":"DA","tot_orders":10,"tot_order_lines":10},{"date":"2021-1-14","action":"SM","tot_orders":112,"tot_order_lines":171},{"date":"2021-1-14","action":"S","tot_orders":25,"tot_order_lines":36},{"date":"2021-1-15","action":"S","tot_orders":7,"tot_order_lines":58},{"date":"2021-1-15","action":"SM","tot_orders":70,"tot_order_lines":120},{"date":"2021-1-15","action":"DA","tot_orders":1,"tot_order_lines":1},{"date":"2021-1-15","action":"DS","tot_orders":81,"tot_order_lines":161},{"date":"2021-1-16","action":"SM","tot_orders":2,"tot_order_lines":24},{"date":"2021-1-16","action":"DS","tot_orders":1,"tot_order_lines":2},{"date":"2021-1-17","action":"SM","tot_orders":4,"tot_order_lines":29},{"date":"2021-1-17","action":"DS","tot_orders":2,"tot_order_lines":4},{"date":"2021-1-18","action":"DA","tot_orders":8,"tot_order_lines":8},{"date":"2021-1-18","action":"S","tot_orders":20,"tot_order_lines":51},{"date":"2021-1-18","action":"DS","tot_orders":255,"tot_order_lines":1583},{"date":"2021-1-18","action":"SM","tot_orders":103,"tot_order_lines":305},{"date":"2021-1-19","action":"S","tot_orders":17,"tot_order_lines":32},{"date":"2021-1-19","action":"DS","tot_orders":218,"tot_order_lines":1008},{"date":"2021-1-19","action":"DA","tot_orders":9,"tot_order_lines":9},{"date":"2021-1-19","action":"SM","tot_orders":139,"tot_order_lines":286},{"date":"2021-1-20","action":"SM","tot_orders":85,"tot_order_lines":239},{"date":"2021-1-20","action":"S","tot_orders":7,"tot_order_lines":10},{"date":"2021-1-20","action":"DA","tot_orders":3,"tot_order_lines":12},{"date":"2021-1-20","action":"DS","tot_orders":184,"tot_order_lines":464},{"date":"2021-1-21","action":"DS","tot_orders":163,"tot_order_lines":483},{"date":"2021-1-21","action":"S","tot_orders":5,"tot_order_lines":5},{"date":"2021-1-21","action":"SM","tot_orders":72,"tot_order_lines":128},{"date":"2021-1-21","action":"DA","tot_orders":12,"tot_order_lines":12},{"date":"2021-1-22","action":"SM","tot_orders":19,"tot_order_lines":27},{"date":"2021-1-22","action":"S","tot_orders":5,"tot_order_lines":10},{"date":"2021-1-22","action":"DA","tot_orders":3,"tot_order_lines":8},{"date":"2021-1-22","action":"DS","tot_orders":76,"tot_order_lines":120},{"date":"2021-1-23","action":"DS","tot_orders":3,"tot_order_lines":12},{"date":"2021-1-24","action":"DS","tot_orders":1,"tot_order_lines":1},{"date":"2021-1-24","action":"SM","tot_orders":4,"tot_order_lines":9},{"date":"2021-1-25","action":"DA","tot_orders":11,"tot_order_lines":11},{"date":"2021-1-25","action":"SM","tot_orders":59,"tot_order_lines":304},{"date":"2021-1-25","action":"S","tot_orders":9,"tot_order_lines":9},{"date":"2021-1-25","action":"DS","tot_orders":244,"tot_order_lines":1353},{"date":"2021-1-26","action":"S","tot_orders":4,"tot_order_lines":5},{"date":"2021-1-26","action":"DS","tot_orders":190,"tot_order_lines":720},{"date":"2021-1-26","action":"SM","tot_orders":103,"tot_order_lines":306},{"date":"2021-1-26","action":"DA","tot_orders":3,"tot_order_lines":4},{"date":"2021-1-27","action":"DS","tot_orders":205,"tot_order_lines":440},{"date":"2021-1-27","action":"DA","tot_orders":2,"tot_order_lines":2},{"date":"2021-1-27","action":"S","tot_orders":5,"tot_order_lines":13},{"date":"2021-1-27","action":"SM","tot_orders":74,"tot_order_lines":220},{"date":"2021-1-28","action":"DS","tot_orders":162,"tot_order_lines":376},{"date":"2021-1-28","action":"SM","tot_orders":54,"tot_order_lines":191},{"date":"2021-1-28","action":"DA","tot_orders":10,"tot_order_lines":12},{"date":"2021-1-28","action":"S","tot_orders":9,"tot_order_lines":17},{"date":"2021-1-29","action":"SM","tot_orders":44,"tot_order_lines":223},{"date":"2021-1-29","action":"DA","tot_orders":4,"tot_order_lines":5},{"date":"2021-1-29","action":"DS","tot_orders":75,"tot_order_lines":159},{"date":"2021-1-29","action":"S","tot_orders":13,"tot_order_lines":14},{"date":"2021-1-30","action":"SM","tot_orders":6,"tot_order_lines":10},{"date":"2021-2-1","action":"DA","tot_orders":10,"tot_order_lines":10},{"date":"2021-2-1","action":"S","tot_orders":20,"tot_order_lines":21},{"date":"2021-2-1","action":"SM","tot_orders":97,"tot_order_lines":238},{"date":"2021-2-1","action":"DS","tot_orders":214,"tot_order_lines":924},{"date":"2021-2-2","action":"SM","tot_orders":102,"tot_order_lines":167},{"date":"2021-2-2","action":"DA","tot_orders":6,"tot_order_lines":7},{"date":"2021-2-2","action":"DS","tot_orders":296,"tot_order_lines":755},{"date":"2021-2-2","action":"S","tot_orders":18,"tot_order_lines":45},{"date":"2021-2-3","action":"S","tot_orders":9,"tot_order_lines":24},{"date":"2021-2-3","action":"SM","tot_orders":94,"tot_order_lines":175},{"date":"2021-2-3","action":"DS","tot_orders":158,"tot_order_lines":329},{"date":"2021-2-3","action":"DA","tot_orders":11,"tot_order_lines":11},{"date":"2021-2-4","action":"DS","tot_orders":151,"tot_order_lines":373},{"date":"2021-2-4","action":"SM","tot_orders":75,"tot_order_lines":105},{"date":"2021-2-4","action":"DA","tot_orders":1,"tot_order_lines":1},{"date":"2021-2-4","action":"S","tot_orders":11,"tot_order_lines":17},{"date":"2021-2-5","action":"SM","tot_orders":72,"tot_order_lines":192},{"date":"2021-2-5","action":"S","tot_orders":3,"tot_order_lines":3},{"date":"2021-2-5","action":"DS","tot_orders":124,"tot_order_lines":389},{"date":"2021-2-5","action":"DA","tot_orders":3,"tot_order_lines":3},{"date":"2021-2-6","action":"SM","tot_orders":1,"tot_order_lines":1},{"date":"2021-2-6","action":"DS","tot_orders":6,"tot_order_lines":7},{"date":"2021-2-7","action":"SM","tot_orders":2,"tot_order_lines":3},{"date":"2021-2-8","action":"DS","tot_orders":213,"tot_order_lines":1010},{"date":"2021-2-8","action":"DA","tot_orders":4,"tot_order_lines":4},{"date":"2021-2-8","action":"S","tot_orders":4,"tot_order_lines":8},{"date":"2021-2-8","action":"SM","tot_orders":95,"tot_order_lines":263},{"date":"2021-2-9","action":"DS","tot_orders":182,"tot_order_lines":658},{"date":"2021-2-9","action":"S","tot_orders":10,"tot_order_lines":21},{"date":"2021-2-9","action":"DA","tot_orders":7,"tot_order_lines":7},{"date":"2021-2-9","action":"SM","tot_orders":158,"tot_order_lines":325},{"date":"2021-2-10","action":"SM","tot_orders":116,"tot_order_lines":208},{"date":"2021-2-10","action":"S","tot_orders":8,"tot_order_lines":15},{"date":"2021-2-10","action":"DS","tot_orders":192,"tot_order_lines":590},{"date":"2021-2-10","action":"DA","tot_orders":3,"tot_order_lines":3},{"date":"2021-2-11","action":"S","tot_orders":21,"tot_order_lines":26},{"date":"2021-2-11","action":"DS","tot_orders":126,"tot_order_lines":551},{"date":"2021-2-11","action":"DA","tot_orders":5,"tot_order_lines":6},{"date":"2021-2-11","action":"SM","tot_orders":145,"tot_order_lines":257},{"date":"2021-2-12","action":"SM","tot_orders":107,"tot_order_lines":146},{"date":"2021-2-12","action":"S","tot_orders":6,"tot_order_lines":6},{"date":"2021-2-12","action":"DS","tot_orders":175,"tot_order_lines":375},{"date":"2021-2-12","action":"DA","tot_orders":7,"tot_order_lines":7},{"date":"2021-2-13","action":"DS","tot_orders":1,"tot_order_lines":1},{"date":"2021-2-14","action":"SM","tot_orders":1,"tot_order_lines":2},{"date":"2021-2-15","action":"S","tot_orders":19,"tot_order_lines":24},{"date":"2021-2-15","action":"DA","tot_orders":17,"tot_order_lines":17},{"date":"2021-2-15","action":"SM","tot_orders":93,"tot_order_lines":259},{"date":"2021-2-15","action":"DS","tot_orders":157,"tot_order_lines":1436},{"date":"2021-2-16","action":"SM","tot_orders":269,"tot_order_lines":568},{"date":"2021-2-16","action":"S","tot_orders":22,"tot_order_lines":30},{"date":"2021-2-16","action":"DS","tot_orders":222,"tot_order_lines":672},{"date":"2021-2-16","action":"DA","tot_orders":2,"tot_order_lines":2},{"date":"2021-2-17","action":"DS","tot_orders":148,"tot_order_lines":462},{"date":"2021-2-17","action":"S","tot_orders":9,"tot_order_lines":14},{"date":"2021-2-17","action":"DA","tot_orders":3,"tot_order_lines":3},{"date":"2021-2-17","action":"SM","tot_orders":148,"tot_order_lines":278},{"date":"2021-2-18","action":"DS","tot_orders":138,"tot_order_lines":426},{"date":"2021-2-18","action":"SM","tot_orders":58,"tot_order_lines":106},{"date":"2021-2-18","action":"S","tot_orders":11,"tot_order_lines":11},{"date":"2021-2-18","action":"DA","tot_orders":6,"tot_order_lines":6},{"date":"2021-2-19","action":"DS","tot_orders":155,"tot_order_lines":302},{"date":"2021-2-19","action":"SM","tot_orders":55,"tot_order_lines":118},{"date":"2021-2-19","action":"S","tot_orders":3,"tot_order_lines":6},{"date":"2021-2-19","action":"DA","tot_orders":13,"tot_order_lines":24},{"date":"2021-2-21","action":"DS","tot_orders":1,"tot_order_lines":1},{"date":"2021-2-22","action":"DS","tot_orders":284,"tot_order_lines":1567},{"date":"2021-2-22","action":"SM","tot_orders":99,"tot_order_lines":247},{"date":"2021-2-22","action":"DA","tot_orders":7,"tot_order_lines":7},{"date":"2021-2-22","action":"S","tot_orders":4,"tot_order_lines":6},{"date":"2021-2-23","action":"S","tot_orders":4,"tot_order_lines":5},{"date":"2021-2-23","action":"SM","tot_orders":83,"tot_order_lines":253},{"date":"2021-2-23","action":"DS","tot_orders":183,"tot_order_lines":558},{"date":"2021-2-23","action":"DA","tot_orders":6,"tot_order_lines":7},{"date":"2021-2-24","action":"DS","tot_orders":189,"tot_order_lines":357},{"date":"2021-2-24","action":"S","tot_orders":7,"tot_order_lines":35},{"date":"2021-2-24","action":"DA","tot_orders":2,"tot_order_lines":3},{"date":"2021-2-24","action":"SM","tot_orders":55,"tot_order_lines":106},{"date":"2021-2-25","action":"SM","tot_orders":74,"tot_order_lines":166},{"date":"2021-2-25","action":"DS","tot_orders":157,"tot_order_lines":435},{"date":"2021-2-25","action":"S","tot_orders":5,"tot_order_lines":10},{"date":"2021-2-25","action":"DA","tot_orders":6,"tot_order_lines":6},{"date":"2021-2-26","action":"DA","tot_orders":14,"tot_order_lines":14},{"date":"2021-2-26","action":"DS","tot_orders":114,"tot_order_lines":329},{"date":"2021-2-26","action":"SM","tot_orders":51,"tot_order_lines":167},{"date":"2021-2-26","action":"S","tot_orders":3,"tot_order_lines":18},{"date":"2021-3-1","action":"DS","tot_orders":219,"tot_order_lines":1608},{"date":"2021-3-1","action":"S","tot_orders":7,"tot_order_lines":11},{"date":"2021-3-1","action":"SM","tot_orders":94,"tot_order_lines":425},{"date":"2021-3-1","action":"DA","tot_orders":11,"tot_order_lines":35},{"date":"2021-3-2","action":"DS","tot_orders":179,"tot_order_lines":552},{"date":"2021-3-2","action":"SM","tot_orders":55,"tot_order_lines":284},{"date":"2021-3-2","action":"S","tot_orders":7,"tot_order_lines":11},{"date":"2021-3-2","action":"DA","tot_orders":3,"tot_order_lines":4},{"date":"2021-3-3","action":"S","tot_orders":16,"tot_order_lines":18},{"date":"2021-3-3","action":"SM","tot_orders":104,"tot_order_lines":362},{"date":"2021-3-3","action":"DA","tot_orders":7,"tot_order_lines":8},{"date":"2021-3-3","action":"DS","tot_orders":185,"tot_order_lines":415},{"date":"2021-3-4","action":"S","tot_orders":16,"tot_order_lines":28},{"date":"2021-3-4","action":"SM","tot_orders":44,"tot_order_lines":68},{"date":"2021-3-4","action":"DS","tot_orders":112,"tot_order_lines":300},{"date":"2021-3-4","action":"DA","tot_orders":4,"tot_order_lines":4},{"date":"2021-3-5","action":"SM","tot_orders":58,"tot_order_lines":105},{"date":"2021-3-5","action":"DA","tot_orders":2,"tot_order_lines":2},{"date":"2021-3-5","action":"S","tot_orders":10,"tot_order_lines":17},{"date":"2021-3-5","action":"DS","tot_orders":106,"tot_order_lines":420},{"date":"2021-3-6","action":"DS","tot_orders":1,"tot_order_lines":1},{"date":"2021-3-8","action":"S","tot_orders":9,"tot_order_lines":11},{"date":"2021-3-8","action":"DA","tot_orders":12,"tot_order_lines":12},{"date":"2021-3-8","action":"SM","tot_orders":75,"tot_order_lines":334},{"date":"2021-3-8","action":"DS","tot_orders":213,"tot_order_lines":1286},{"date":"2021-3-9","action":"DS","tot_orders":190,"tot_order_lines":809},{"date":"2021-3-9","action":"SM","tot_orders":102,"tot_order_lines":279},{"date":"2021-3-9","action":"DA","tot_orders":3,"tot_order_lines":3},{"date":"2021-3-9","action":"S","tot_orders":10,"tot_order_lines":17},{"date":"2021-3-10","action":"S","tot_orders":5,"tot_order_lines":6},{"date":"2021-3-10","action":"DS","tot_orders":147,"tot_order_lines":336},{"date":"2021-3-10","action":"DA","tot_orders":1,"tot_order_lines":1},{"date":"2021-3-10","action":"SM","tot_orders":98,"tot_order_lines":199},{"date":"2021-3-11","action":"SM","tot_orders":57,"tot_order_lines":105},{"date":"2021-3-11","action":"S","tot_orders":4,"tot_order_lines":4},{"date":"2021-3-11","action":"DS","tot_orders":162,"tot_order_lines":371},{"date":"2021-3-11","action":"DA","tot_orders":8,"tot_order_lines":8},{"date":"2021-3-12","action":"SM","tot_orders":100,"tot_order_lines":200},{"date":"2021-3-12","action":"S","tot_orders":6,"tot_order_lines":10},{"date":"2021-3-12","action":"DS","tot_orders":93,"tot_order_lines":496},{"date":"2021-3-13","action":"DS","tot_orders":2,"tot_order_lines":2},{"date":"2021-3-14","action":"DS","tot_orders":3,"tot_order_lines":15},{"date":"2021-3-14","action":"SM","tot_orders":4,"tot_order_lines":4},{"date":"2021-3-15","action":"S","tot_orders":12,"tot_order_lines":21},{"date":"2021-3-15","action":"DA","tot_orders":7,"tot_order_lines":7},{"date":"2021-3-15","action":"SM","tot_orders":102,"tot_order_lines":482},{"date":"2021-3-15","action":"DS","tot_orders":295,"tot_order_lines":1458},{"date":"2021-3-16","action":"DA","tot_orders":6,"tot_order_lines":7},{"date":"2021-3-16","action":"DS","tot_orders":233,"tot_order_lines":700},{"date":"2021-3-16","action":"SM","tot_orders":73,"tot_order_lines":203},{"date":"2021-3-16","action":"S","tot_orders":11,"tot_order_lines":18},{"date":"2021-3-17","action":"S","tot_orders":7,"tot_order_lines":46},{"date":"2021-3-17","action":"DS","tot_orders":145,"tot_order_lines":438},{"date":"2021-3-17","action":"SM","tot_orders":57,"tot_order_lines":139},{"date":"2021-3-17","action":"DA","tot_orders":1,"tot_order_lines":1},{"date":"2021-3-18","action":"DS","tot_orders":141,"tot_order_lines":398},{"date":"2021-3-18","action":"SM","tot_orders":67,"tot_order_lines":121},{"date":"2021-3-18","action":"S","tot_orders":13,"tot_order_lines":27},{"date":"2021-3-18","action":"DA","tot_orders":4,"tot_order_lines":4},{"date":"2021-3-19","action":"SM","tot_orders":86,"tot_order_lines":180},{"date":"2021-3-19","action":"S","tot_orders":22,"tot_order_lines":105},{"date":"2021-3-19","action":"DS","tot_orders":138,"tot_order_lines":260},{"date":"2021-3-19","action":"DA","tot_orders":4,"tot_order_lines":4},{"date":"2021-3-20","action":"S","tot_orders":2,"tot_order_lines":2},{"date":"2021-3-20","action":"DS","tot_orders":1,"tot_order_lines":1},{"date":"2021-3-22","action":"SM","tot_orders":80,"tot_order_lines":336},{"date":"2021-3-22","action":"S","tot_orders":14,"tot_order_lines":38},{"date":"2021-3-22","action":"DA","tot_orders":11,"tot_order_lines":12},{"date":"2021-3-22","action":"DS","tot_orders":235,"tot_order_lines":1421},{"date":"2021-3-23","action":"DS","tot_orders":221,"tot_order_lines":926},{"date":"2021-3-23","action":"S","tot_orders":5,"tot_order_lines":10},{"date":"2021-3-23","action":"DA","tot_orders":1,"tot_order_lines":1},{"date":"2021-3-23","action":"SM","tot_orders":115,"tot_order_lines":317},{"date":"2021-3-24","action":"DA","tot_orders":2,"tot_order_lines":2},{"date":"2021-3-24","action":"S","tot_orders":1,"tot_order_lines":6},{"date":"2021-3-24","action":"SM","tot_orders":84,"tot_order_lines":204},{"date":"2021-3-24","action":"DS","tot_orders":198,"tot_order_lines":360},{"date":"2021-3-25","action":"DS","tot_orders":162,"tot_order_lines":368},{"date":"2021-3-25","action":"SM","tot_orders":64,"tot_order_lines":177},{"date":"2021-3-25","action":"S","tot_orders":4,"tot_order_lines":4},{"date":"2021-3-25","action":"DA","tot_orders":7,"tot_order_lines":7},{"date":"2021-3-26","action":"DS","tot_orders":87,"tot_order_lines":204},{"date":"2021-3-26","action":"SM","tot_orders":66,"tot_order_lines":158},{"date":"2021-3-26","action":"S","tot_orders":11,"tot_order_lines":87},{"date":"2021-3-26","action":"DA","tot_orders":1,"tot_order_lines":1},{"date":"2021-3-27","action":"S","tot_orders":9,"tot_order_lines":10},{"date":"2021-3-27","action":"SM","tot_orders":1,"tot_order_lines":1},{"date":"2021-3-28","action":"SM","tot_orders":1,"tot_order_lines":1},{"date":"2021-3-28","action":"DS","tot_orders":1,"tot_order_lines":1},{"date":"2021-3-29","action":"DS","tot_orders":212,"tot_order_lines":1752},{"date":"2021-3-29","action":"SM","tot_orders":80,"tot_order_lines":371},{"date":"2021-3-29","action":"DA","tot_orders":4,"tot_order_lines":4},{"date":"2021-3-29","action":"S","tot_orders":17,"tot_order_lines":34},{"date":"2021-3-30","action":"S","tot_orders":13,"tot_order_lines":27},{"date":"2021-3-30","action":"DS","tot_orders":147,"tot_order_lines":408},{"date":"2021-3-30","action":"DA","tot_orders":6,"tot_order_lines":8},{"date":"2021-3-30","action":"SM","tot_orders":67,"tot_order_lines":122},{"date":"2021-3-31","action":"DS","tot_orders":148,"tot_order_lines":437},{"date":"2021-3-31","action":"SM","tot_orders":68,"tot_order_lines":159},{"date":"2021-3-31","action":"DA","tot_orders":1,"tot_order_lines":1},{"date":"2021-3-31","action":"S","tot_orders":6,"tot_order_lines":35},{"date":"2021-4-1","action":"DA","tot_orders":4,"tot_order_lines":4},{"date":"2021-4-1","action":"S","tot_orders":7,"tot_order_lines":8},{"date":"2021-4-1","action":"SM","tot_orders":119,"tot_order_lines":195},{"date":"2021-4-1","action":"DS","tot_orders":133,"tot_order_lines":301},{"date":"2021-4-2","action":"S","tot_orders":3,"tot_order_lines":3},{"date":"2021-4-2","action":"DA","tot_orders":3,"tot_order_lines":3},{"date":"2021-4-2","action":"DS","tot_orders":99,"tot_order_lines":267},{"date":"2021-4-2","action":"SM","tot_orders":86,"tot_order_lines":118},{"date":"2021-4-5","action":"SM","tot_orders":89,"tot_order_lines":410},{"date":"2021-4-5","action":"DA","tot_orders":7,"tot_order_lines":7},{"date":"2021-4-5","action":"DS","tot_orders":181,"tot_order_lines":1007},{"date":"2021-4-5","action":"S","tot_orders":7,"tot_order_lines":7},{"date":"2021-4-6","action":"DS","tot_orders":208,"tot_order_lines":893},{"date":"2021-4-6","action":"S","tot_orders":11,"tot_order_lines":21},{"date":"2021-4-6","action":"SM","tot_orders":140,"tot_order_lines":240},{"date":"2021-4-6","action":"DA","tot_orders":5,"tot_order_lines":5},{"date":"2021-4-7","action":"S","tot_orders":2,"tot_order_lines":6},{"date":"2021-4-7","action":"DA","tot_orders":6,"tot_order_lines":6},{"date":"2021-4-7","action":"DS","tot_orders":167,"tot_order_lines":413},{"date":"2021-4-7","action":"SM","tot_orders":116,"tot_order_lines":233},{"date":"2021-4-8","action":"DA","tot_orders":4,"tot_order_lines":4},{"date":"2021-4-8","action":"SM","tot_orders":87,"tot_order_lines":184},{"date":"2021-4-8","action":"DS","tot_orders":143,"tot_order_lines":350},{"date":"2021-4-8","action":"S","tot_orders":9,"tot_order_lines":9},{"date":"2021-4-9","action":"S","tot_orders":7,"tot_order_lines":7},{"date":"2021-4-9","action":"SM","tot_orders":67,"tot_order_lines":87},{"date":"2021-4-9","action":"DA","tot_orders":4,"tot_order_lines":4},{"date":"2021-4-9","action":"DS","tot_orders":107,"tot_order_lines":400},{"date":"2021-4-12","action":"DS","tot_orders":207,"tot_order_lines":787},{"date":"2021-4-12","action":"SM","tot_orders":89,"tot_order_lines":311},{"date":"2021-4-12","action":"DA","tot_orders":13,"tot_order_lines":15},{"date":"2021-4-12","action":"S","tot_orders":8,"tot_order_lines":9},{"date":"2021-4-13","action":"DS","tot_orders":201,"tot_order_lines":1230},{"date":"2021-4-13","action":"S","tot_orders":5,"tot_order_lines":8},{"date":"2021-4-13","action":"SM","tot_orders":97,"tot_order_lines":243},{"date":"2021-4-13","action":"DA","tot_orders":4,"tot_order_lines":4},{"date":"2021-4-14","action":"DS","tot_orders":126,"tot_order_lines":314},{"date":"2021-4-14","action":"DA","tot_orders":2,"tot_order_lines":3},{"date":"2021-4-14","action":"SM","tot_orders":63,"tot_order_lines":127},{"date":"2021-4-14","action":"S","tot_orders":3,"tot_order_lines":3},{"date":"2021-4-15","action":"S","tot_orders":6,"tot_order_lines":11},{"date":"2021-4-15","action":"DS","tot_orders":206,"tot_order_lines":533},{"date":"2021-4-15","action":"SM","tot_orders":62,"tot_order_lines":90},{"date":"2021-4-16","action":"S","tot_orders":4,"tot_order_lines":8},{"date":"2021-4-16","action":"DS","tot_orders":84,"tot_order_lines":244},{"date":"2021-4-16","action":"SM","tot_orders":63,"tot_order_lines":140}]}